pyuno/__init__.py
uno/__init__.py
unohelper/__init__.py
api_unostubs-0.2.0.dist-info/LICENSE
api_unostubs-0.2.0.dist-info/METADATA
api_unostubs-0.2.0.dist-info/WHEEL
api_unostubs-0.2.0.dist-info/RECORD
